{
    "name": "Inscribed Pepes",
    "supply": "69",
    "range":"2115-2189" ,
    "about": "This collection is a part of sub 10k club.\nThe First and rarest 69 pixelated Pepes inscribed until the end of time on the Bitcoin blockchain. ",
    "how-to-buy":"https://ordinalswallet.com/collection/inscribed-pepes" ,
    "value-proposiion":"-",
    "roadmap":"-",
    "mint-status":"-",
    "team":"@0wl#7511",
    "additional-links":"-",
    "twitter_link": "https://twitter.com/InscribedPepe",
    "discord_link": "https://discord.gg/inscribedpepes",
    "website_link": ""
}